mpcmd/__init__.py
mpcmd/base.py
mpcmd/mpcd.py
mpcmd/collide/__init__.py
mpcmd/collide/collide.py
mpcmd/compute/__init__.py
mpcmd/geometry/__init__.py
mpcmd/geometry/cubic.py
mpcmd/geometry/cylinder.py
mpcmd/geometry/geometry.py
mpcmd/md/__init__.py
mpcmd/md/hoomd_.py
mpcmd/md/lammps_.py
mpcmd/md/pymd.py
mpcmd/stream/__init__.py
mpcmd/stream/poiseuille.py
mpcmd/stream/shear.py
mpcmd/stream/stream.py
mpcmd/tools/__init__.py
mpcmd/tools/compute_vcm.py
mpcmd/tools/make_gsd_snapshot.py
mpcmd/tools/parse_boundary.py
mpcmd-0.0.6.dist-info/LICENSE
mpcmd-0.0.6.dist-info/METADATA
mpcmd-0.0.6.dist-info/WHEEL
mpcmd-0.0.6.dist-info/top_level.txt
mpcmd-0.0.6.dist-info/RECORD
