Metadata-Version: 2.1
Name: mpcmd
Version: 0.0.6
Summary: A python-based simulation package using mpcd and md.
Home-page: https://github.com/dotmet/mpcmd
Author: Even Wong
Author-email: wdyphy@zju.edu.cn
Requires-Python: >=3.0
License-File: LICENSE
Requires-Dist: matplotlib
Requires-Dist: numpy
Requires-Dist: scipy
Requires-Dist: numba
Requires-Dist: gsd
Requires-Dist: memory-profiler
Requires-Dist: seaborn
Requires-Dist: scikit-learn
